decord/__init__.py
decord/_api_internal.py
decord/audio_reader.py
decord/av_reader.py
decord/base.py
decord/libdecord.dylib
decord/logging.py
decord/ndarray.py
decord/video_loader.py
decord/video_reader.py
decord/_ffi/__init__.py
decord/_ffi/base.py
decord/_ffi/function.py
decord/_ffi/libinfo.py
decord/_ffi/ndarray.py
decord/_ffi/runtime_ctypes.py
decord/_ffi/_ctypes/__init__.py
decord/_ffi/_ctypes/function.py
decord/_ffi/_ctypes/ndarray.py
decord/_ffi/_ctypes/types.py
decord/_ffi/_cy2/__init__.py
decord/_ffi/_cy3/__init__.py
decord/bridge/__init__.py
decord/bridge/mxnet.py
decord/bridge/tf.py
decord/bridge/torchdl.py
decord/bridge/tvm.py
decord/bridge/utils.py
decord/data/__init__.py
decord/data/base_action.py
decord/data/dataloader.py
decord/data/kinetics/__init__.py
decord/data/kinetics/kinetics400_action.py
decord/data/transforms/__init__.py
decord/data/transforms/action.py
decord/function/__init__.py
decord/function/base.py
eva_decord_plus-0.6.2.dist-info/METADATA
eva_decord_plus-0.6.2.dist-info/WHEEL
eva_decord_plus-0.6.2.dist-info/top_level.txt
eva_decord_plus-0.6.2.dist-info/RECORD
